MSIght/__init__.py
MSIght/launch_advanced_notebook.py
MSIght/launch_basic_notebook.py
MSIght/refactor_affine_transform.py
MSIght/refactor_bspline.py
MSIght/refactor_cluster_optimize.py
MSIght/refactor_common_functions.py
MSIght/refactor_fragger_process.py
MSIght/refactor_he_lcmsms_msi_merge.py
MSIght/refactor_histology_preprocess.py
MSIght/refactor_interpolation.py
MSIght/refactor_manual_affine.py
MSIght/refactor_manual_affine_transform.py
MSIght/refactor_mz_image_extract.py
MSIght/refactor_segment.py
MSIght/run_pytest.py
MSIght/__pycache__/__init__.cpython-39.pyc
MSIght/__pycache__/refactor_affine_transform.cpython-39.pyc
MSIght/__pycache__/refactor_bspline.cpython-39.pyc
MSIght/__pycache__/refactor_cluster_optimize.cpython-39.pyc
MSIght/__pycache__/refactor_common_functions.cpython-39.pyc
MSIght/__pycache__/refactor_histology_preprocess.cpython-39.pyc
MSIght/__pycache__/refactor_interpolation.cpython-39.pyc
MSIght/__pycache__/refactor_manual_affine.cpython-39.pyc
MSIght/__pycache__/refactor_segment.cpython-39.pyc
msight-1.0.24.dist-info/licenses/LICENSE
notebooks/__init__.py
notebooks/advanced_workflow.ipynb
notebooks/basic_workflow.ipynb
notebooks/.ipynb_checkpoints/advanced_workflow-checkpoint.ipynb
notebooks/.ipynb_checkpoints/basic_workflow-checkpoint.ipynb
notebooks/MSIght_Jupyter/__init__.py
notebooks/MSIght_Jupyter/refactor_affine_transform.py
notebooks/MSIght_Jupyter/refactor_bspline.py
notebooks/MSIght_Jupyter/refactor_cluster_optimize.py
notebooks/MSIght_Jupyter/refactor_common_functions.py
notebooks/MSIght_Jupyter/refactor_fragger_process.py
notebooks/MSIght_Jupyter/refactor_he_lcmsms_msi_merge.py
notebooks/MSIght_Jupyter/refactor_histology_preprocess.py
notebooks/MSIght_Jupyter/refactor_interpolation.py
notebooks/MSIght_Jupyter/refactor_manual_affine.py
notebooks/MSIght_Jupyter/refactor_manual_affine_transform.py
notebooks/MSIght_Jupyter/refactor_msfragger.py
notebooks/MSIght_Jupyter/refactor_mz_image_extract.py
notebooks/MSIght_Jupyter/refactor_segment.py
msight-1.0.24.dist-info/METADATA
msight-1.0.24.dist-info/WHEEL
msight-1.0.24.dist-info/entry_points.txt
msight-1.0.24.dist-info/top_level.txt
msight-1.0.24.dist-info/RECORD
